funny_morse/__init__.py
funny_morse/__main__.py
funny_morse/key.py
funny_morse/morse.py
funny_morse/morseTable.py
funny_morse/parallel.py
funny_morse/play.py
funny_morse/pyboard.py
funny_morse/show.py
funny_morse-0.0.1.dist-info/WHEEL
funny_morse-0.0.1.dist-info/METADATA
funny_morse-0.0.1.dist-info/RECORD
