Metadata-Version: 2.1
Name: funny-morse
Version: 0.0.1
Summary: Converts text to morse code signals [audio, window, keyboardleds, led, servo]
Home-page: https://github.com/nkpro2000sr/funny-morse
License: MIT
Keywords: morse,funny,morse2signal,all,play-show-tap
Author: Naveen S R
Author-email: srnaveen2k@yahoo.com
Maintainer: Naveen S R
Maintainer-email: srnaveen2k@yahoo.com
Requires-Python: >=3.6
Classifier: License :: OSI Approved :: MIT License
Classifier: Programming Language :: Python :: 3
Classifier: Programming Language :: Python :: 3.6
Classifier: Programming Language :: Python :: 3.7
Classifier: Programming Language :: Python :: 3.8
Requires-Dist: numpy (>=1.7)
Requires-Dist: pynput (>=1.6)
Requires-Dist: rshell (>=0.0.20)
Requires-Dist: sounddevice (>=0.3)
Requires-Dist: wavio (>=0.0.1)
Project-URL: Repository, https://github.com/nkpro2000sr/funny-morse
